endex_factset_estimates/__init__.py
endex_factset_estimates/_base_client.py
endex_factset_estimates/_client.py
endex_factset_estimates/_compat.py
endex_factset_estimates/_constants.py
endex_factset_estimates/_exceptions.py
endex_factset_estimates/_files.py
endex_factset_estimates/_models.py
endex_factset_estimates/_qs.py
endex_factset_estimates/_resource.py
endex_factset_estimates/_response.py
endex_factset_estimates/_streaming.py
endex_factset_estimates/_types.py
endex_factset_estimates/_version.py
endex_factset_estimates/py.typed
endex_factset_estimates/_utils/__init__.py
endex_factset_estimates/_utils/_logs.py
endex_factset_estimates/_utils/_proxy.py
endex_factset_estimates/_utils/_reflection.py
endex_factset_estimates/_utils/_streams.py
endex_factset_estimates/_utils/_sync.py
endex_factset_estimates/_utils/_transform.py
endex_factset_estimates/_utils/_typing.py
endex_factset_estimates/_utils/_utils.py
endex_factset_estimates/lib/.keep
endex_factset_estimates/resources/__init__.py
endex_factset_estimates/resources/factset_estimates/__init__.py
endex_factset_estimates/resources/factset_estimates/factset_estimates.py
endex_factset_estimates/resources/factset_estimates/v2/__init__.py
endex_factset_estimates/resources/factset_estimates/v2/consensus_ratings.py
endex_factset_estimates/resources/factset_estimates/v2/detail_ratings.py
endex_factset_estimates/resources/factset_estimates/v2/fixed_consensus.py
endex_factset_estimates/resources/factset_estimates/v2/fixed_detail.py
endex_factset_estimates/resources/factset_estimates/v2/metrics.py
endex_factset_estimates/resources/factset_estimates/v2/rolling_consensus.py
endex_factset_estimates/resources/factset_estimates/v2/rolling_detail.py
endex_factset_estimates/resources/factset_estimates/v2/segments.py
endex_factset_estimates/resources/factset_estimates/v2/surprise.py
endex_factset_estimates/resources/factset_estimates/v2/v2.py
endex_factset_estimates/types/__init__.py
endex_factset_estimates-0.1.0a1.dist-info/METADATA
endex_factset_estimates-0.1.0a1.dist-info/WHEEL
endex_factset_estimates-0.1.0a1.dist-info/licenses/LICENSE
endex_factset_estimates-0.1.0a1.dist-info/RECORD
